subcommand.py
cli_subcommand-1.0.1.dist-info/DESCRIPTION.rst
cli_subcommand-1.0.1.dist-info/METADATA
cli_subcommand-1.0.1.dist-info/RECORD
cli_subcommand-1.0.1.dist-info/WHEEL
cli_subcommand-1.0.1.dist-info/metadata.json
cli_subcommand-1.0.1.dist-info/top_level.txt
