Metadata-Version: 2.0
Name: cli-subcommand
Version: 1.0.1
Summary: Sub Command line parser for python CLI scripts
Home-page: http://thrawn01.org/sub-command
Author: Derrick J. Wippler
Author-email: thrawn01@gmail.com
License: Apache 2.0
Platform: UNKNOWN
Classifier: Development Status :: 5 - Production/Stable
Classifier: Intended Audience :: Developers
Classifier: Natural Language :: English
Classifier: License :: OSI Approved :: Apache Software License
Classifier: Programming Language :: Python
Classifier: Programming Language :: Python :: 2.6
Classifier: Programming Language :: Python :: 2.7
Classifier: Programming Language :: Python :: 3
Classifier: Programming Language :: Python :: 3.3
Classifier: Programming Language :: Python :: 3.4
